streamlit_activities_menu/__init__.py
streamlit_activities_menu/example_app/__init__.py
streamlit_activities_menu/example_app/activities/data_processing.py
streamlit_activities_menu/example_app/activities/main.py
streamlit_activities_menu/example_app/activities/map.py
streamlit_activities_menu/example_app/app_activities.yaml
streamlit_activities_menu/example_app/streamlit_app.py
streamlit_activities_menu/requirements.txt
streamlit_activities_menu/version.py
streamlit_activities_menu-0.1.4.dist-info/METADATA
streamlit_activities_menu-0.1.4.dist-info/WHEEL
streamlit_activities_menu-0.1.4.dist-info/RECORD
