Metadata-Version: 2.1
Name: streamlit-activities-menu
Version: 0.1.4
Summary: 
Author: Jobelund
Author-email: 124563223+jobelund@users.noreply.github.com
Requires-Python: >=3.9, !=2.7.*, !=3.0.*, !=3.1.*, !=3.2.*, !=3.3.*, !=3.4.*, !=3.5.*, !=3.6.*, !=3.7.*, !=3.8.*
Classifier: Programming Language :: Python :: 3
Classifier: Programming Language :: Python :: 3.9
Classifier: Programming Language :: Python :: 3.10
Classifier: Programming Language :: Python :: 3.11
Classifier: Programming Language :: Python :: 3.12
Requires-Dist: mkdocs (>=1.5.3,<2.0.0)
Requires-Dist: pytest (>=7.4.3,<8.0.0)
Requires-Dist: pyyaml (>=6.0.1,<7.0.0)
Requires-Dist: streamlit (>=1.18,<2.0)
